pretty_traceback/__init__.py
pretty_traceback/common.py
pretty_traceback/formatting.py
pretty_traceback/hook.py
pretty_traceback/parsing.py
pretty_traceback-2024.1021.dist-info/LICENSE
pretty_traceback-2024.1021.dist-info/METADATA
pretty_traceback-2024.1021.dist-info/WHEEL
pretty_traceback-2024.1021.dist-info/top_level.txt
pretty_traceback-2024.1021.dist-info/zip-safe
pretty_traceback-2024.1021.dist-info/RECORD
