Metadata-Version: 2.1
Name: pretty-traceback
Version: 2024.1021
Summary: Human readable stacktraces.
Home-page: https://github.com/mbarkhau/pretty-traceback
Author: Manuel Barkhau
Author-email: mbarkhau@gmail.com
License: MIT
Keywords: traceback stacktrace pretty
Classifier: Development Status :: 4 - Beta
Classifier: Environment :: Console
Classifier: Environment :: Other Environment
Classifier: Intended Audience :: Developers
Classifier: License :: OSI Approved :: MIT License
Classifier: Operating System :: Unix
Classifier: Operating System :: POSIX
Classifier: Operating System :: MacOS :: MacOS X
Classifier: Operating System :: Microsoft :: Windows
Classifier: Programming Language :: Python
Classifier: Programming Language :: Python :: 2
Classifier: Programming Language :: Python :: 3
Classifier: Programming Language :: Python :: Implementation :: CPython
Classifier: Programming Language :: Python :: Implementation :: PyPy
Classifier: Topic :: Software Development :: Libraries
Classifier: Topic :: Software Development :: Libraries :: Python Modules
Requires-Python: >=2.7
License-File: LICENSE
Requires-Dist: typing ; python_version < "3.5"
Requires-Dist: colorama <0.4,>=0.3.9 ; python_version < "3.6"
Requires-Dist: colorama >=0.4 ; python_version >= "3.6"
